quimeraps/__init__.py
quimeraps/entry_points.py
quimeraps/single_proccess.py
quimeraps/client_gui/__init__.py
quimeraps/client_gui/main_window.py
quimeraps/client_gui/main_window.ui
quimeraps/json_srv/SMWinservice.py
quimeraps/json_srv/__init__.py
quimeraps/json_srv/daemon_functions.py
quimeraps/json_srv/data.py
quimeraps/json_srv/logging.py
quimeraps/json_srv/main_service.py
quimeraps/json_srv/process_functions.py
quimeraps/json_srv/utils.py
quimeraps-0.93.1.dist-info/LICENSE.gplv3
quimeraps-0.93.1.dist-info/METADATA
quimeraps-0.93.1.dist-info/WHEEL
quimeraps-0.93.1.dist-info/entry_points.txt
quimeraps-0.93.1.dist-info/top_level.txt
quimeraps-0.93.1.dist-info/RECORD
