Metadata-Version: 2.1
Name: quimeraps
Version: 0.93.1
Summary: Quimera Print Service
Home-page: 
Author: José A. Fernández Fernández
Author-email: aullasistemas@gmail.com
Keywords: eneboo pineboo printer json
Classifier: Development Status :: 4 - Beta
Classifier: License :: OSI Approved :: MIT License
Classifier: Programming Language :: Python :: 3 :: Only
Classifier: Programming Language :: Python :: 3
Classifier: Programming Language :: Python :: 3.6
Classifier: Programming Language :: Python :: 3.7
Classifier: Programming Language :: Python :: 3.8
Classifier: Programming Language :: Python :: 3.9
Classifier: Environment :: X11 Applications :: Qt
Classifier: Topic :: Office/Business :: Financial :: Accounting
Classifier: Typing :: Typed
Classifier: Intended Audience :: End Users/Desktop
Classifier: Intended Audience :: Developers
Classifier: Natural Language :: English
Classifier: Natural Language :: Spanish
Classifier: Operating System :: OS Independent
Requires-Python: >=3.6.9
License-File: LICENSE.gplv3
Requires-Dist: werkzeug ==3.0.3
Requires-Dist: json-rpc ==1.13.0
Requires-Dist: PyQt5 ==5.15.11
Requires-Dist: ghostscript ==0.7
Requires-Dist: fastapi
Requires-Dist: gunicorn
Requires-Dist: flask
